pylenza/__init__.py
pylenza/arrays.py
pylenza/linkedlist.py
pylenza/queue.py
pylenza/recursion.py
pylenza/search.py
pylenza/sort.py
pylenza/stack.py
pylenza/strings.py
pylenza/trees.py
pylenza-0.1.2.dist-info/licenses/LICENCE
pylenza-0.1.2.dist-info/METADATA
pylenza-0.1.2.dist-info/WHEEL
pylenza-0.1.2.dist-info/top_level.txt
pylenza-0.1.2.dist-info/RECORD
