Metadata-Version: 2.4
Name: pylenza
Version: 0.1.2
Summary: A beginner-friendly Python package for learning data structures, algorithms, recursion, and logic.
Author: Vedant Shukla
Author-email: Vedant Shukla <vedantshukla1056@gmail.com>
License: MIT
Project-URL: Homepage, https://github.com/Vedant839/pylenza
Project-URL: Repository, https://github.com/Vedant839/pylenza
Requires-Python: >=3.10
License-File: LICENCE
Provides-Extra: numpy
Requires-Dist: numpy>=1.24.0; extra == "numpy"
Dynamic: license-file
